setup.py
src/pypi_switcher/__init__.py
src/pypi_switcher/__version__.py
src/pypi_switcher.egg-info/PKG-INFO
src/pypi_switcher.egg-info/SOURCES.txt
src/pypi_switcher.egg-info/dependency_links.txt
src/pypi_switcher.egg-info/entry_points.txt
src/pypi_switcher.egg-info/namespace_packages.txt
src/pypi_switcher.egg-info/not-zip-safe
src/pypi_switcher.egg-info/requires.txt
src/pypi_switcher.egg-info/top_level.txt