Metadata-Version: 1.1
Name: pypi_switcher
Version: 0.1
Summary: a script for switching between pypi servers
Home-page: http://github.com/grzn/pypi_switcher
Author: Guy Rozendorn
Author-email: guy@rzn.co.il
License: PSF
Platform: UNKNOWN
Classifier: Intended Audience :: Developers
Classifier: Intended Audience :: System Administrators
Classifier: License :: OSI Approved :: Python Software Foundation License
Classifier: Operating System :: OS Independent
Classifier: Programming Language :: Python
Classifier: Topic :: Software Development :: Libraries :: Python Modules
